zcooldl/__init__.py
zcooldl/cli.py
zcooldl/utils.py
zcooldl/zcooldl.py
zcooldl-0.1.4.dist-info/AUTHORS.rst
zcooldl-0.1.4.dist-info/LICENSE
zcooldl-0.1.4.dist-info/METADATA
zcooldl-0.1.4.dist-info/WHEEL
zcooldl-0.1.4.dist-info/entry_points.txt
zcooldl-0.1.4.dist-info/top_level.txt
zcooldl-0.1.4.dist-info/RECORD
