Metadata-Version: 2.1
Name: zcooldl
Version: 0.1.4
Summary: ZCool picture crawler. Download ZCool (https://www.zcool.com.cn/) Designer's or User's pictures, photos and illustrations.
Home-page: https://github.com/lonsty/zcooldl
Author: Allen Shaw
Author-email: lonsty@sina.com
License: MIT license
Keywords: zcooldl,zcool,picture,download,downloader
Platform: UNKNOWN
Classifier: Development Status :: 2 - Pre-Alpha
Classifier: Intended Audience :: Developers
Classifier: License :: OSI Approved :: MIT License
Classifier: Natural Language :: English
Classifier: Programming Language :: Python :: 3
Classifier: Programming Language :: Python :: 3.6
Classifier: Programming Language :: Python :: 3.7
Classifier: Programming Language :: Python :: 3.8
Requires-Python: >=3.6
Requires-Dist: Click (>=7.0)
Requires-Dist: beautifulsoup4 (>=4.9.1)
Requires-Dist: requests (>=2.24.0)
Requires-Dist: termcolor (>=1.1.0)
